ezpi/__init__.py
ezpi/py.typed
ezpi-0.5.1.dist-info/licenses/COPYING
ezpi-0.5.1.dist-info/METADATA
ezpi-0.5.1.dist-info/WHEEL
ezpi-0.5.1.dist-info/entry_points.txt
ezpi-0.5.1.dist-info/top_level.txt
ezpi-0.5.1.dist-info/RECORD
