Metadata-Version: 2.4
Name: ezpi
Version: 0.5.1
Summary: A simple library to write content to public-inbox repositories
Home-page: https://sr.ht/~monsieuricon/ezpi/
Author: Konstantin Ryabitsev
Author-email: Konstantin Ryabitsev <mricon@kernel.org>
License-Expression: MIT-0
Project-URL: Homepage, https://sr.ht/~monsieuricon/ezpi/
Project-URL: Documentation, https://ezpi.readthedocs.io/
Keywords: git,lore.kernel.org,public-inbox
Requires-Python: >=3.9
License-File: COPYING
Provides-Extra: docs
Requires-Dist: sphinx>=7.0; extra == "docs"
Requires-Dist: sphinx-rtd-theme>=2.0; extra == "docs"
Provides-Extra: libgit2
Requires-Dist: pygit2>=1.12; extra == "libgit2"
Dynamic: license-file
